shoedog/__init__.py
shoedog/api.py
shoedog/ast.py
shoedog/consts.py
shoedog/errors.py
shoedog/eval.py
shoedog/parser.py
shoedog/query_factory.py
shoedog/registry.py
shoedog/serializer.py
shoedog/tokenizer.py
shoedog/utils.py
tests/__init__.py
tests/conftest.py
tests/mock_app.py
tests/test_eval.py
tests/test_parser.py
tests/test_query_factory.py
tests/test_tokenizer.py
shoedog-0.0.1.dist-info/LICENSE
shoedog-0.0.1.dist-info/METADATA
shoedog-0.0.1.dist-info/WHEEL
shoedog-0.0.1.dist-info/top_level.txt
shoedog-0.0.1.dist-info/RECORD
