Metadata-Version: 2.1
Name: shoedog
Version: 0.0.1
Summary: A search tool built on SQLAlchemy
Home-page: https://github.com/jaychia/shoedog
Author: Jay Chia
Author-email: jaychia04@gmail.com
License: UNKNOWN
Platform: UNKNOWN
Classifier: Programming Language :: Python :: 3.6
Classifier: License :: OSI Approved :: MIT License
Classifier: Operating System :: OS Independent
